MANIFEST.in
requirements.txt
setup.py
version.json
fafafa/__init__.py
fafafa/fa_decorator.py
fafafa/fa_hash.py
fafafa/fa_inspect.py
fafafa/fa_json.py
fafafa/fa_limits.py
fafafa/fa_list_all.py
fafafa/fa_mongodb.py
fafafa/fa_patterns.py
fafafa/fa_redis.py
fafafa/fa_requests.py
fafafa/fa_url.py
fafafa/fa_uuid.py
fafafa/fa_value.py
fafafa/fa_xml.py
fafafa.egg-info/PKG-INFO
fafafa.egg-info/SOURCES.txt
fafafa.egg-info/dependency_links.txt
fafafa.egg-info/requires.txt
fafafa.egg-info/top_level.txt